credsleuth/__init__.py
credsleuth/rules.json
credsleuth/sample.txt
credsleuth-0.0.19.data/scripts/credsleuth
credsleuth-0.0.19.dist-info/METADATA
credsleuth-0.0.19.dist-info/RECORD
credsleuth-0.0.19.dist-info/WHEEL
credsleuth-0.0.19.dist-info/top_level.txt
