Metadata-Version: 2.1
Name: credsleuth
Version: 0.0.19
Summary: A rule based library to help identify credentials and secrets in files and strings.
Home-page: https://github.com/rikkouri/credsleuth
Author: Dave Davison
Author-email: dave.davison@hotmail.com
License: UNKNOWN
Platform: UNKNOWN
Classifier: Programming Language :: Python :: 3
Classifier: License :: OSI Approved :: GNU General Public License (GPL)
Classifier: Operating System :: OS Independent
